{"version":2,"kind":"Article","sha256":"d930a2a4beceb06d5fc95042375b29ff7d8eab4df965b836bfa7dc2f9bd2ce3d","slug":"index","location":"/README.md","dependencies":[],"frontmatter":{"title":"(Replace_with_your_title) Cookbook","content_includes_title":false,"authors":[{"nameParsed":{"literal":"The Project Pythia Community","given":"The Project Pythia","family":"Community"},"name":"The Project Pythia Community","id":"contributors-myst-generated-uid-0"}],"open_access":true,"license":{"content":{"id":"CC-BY-4.0","url":"https://creativecommons.org/licenses/by/4.0/","name":"Creative Commons Attribution 4.0 International","free":true,"CC":true},"code":{"id":"Apache-2.0","url":"https://opensource.org/licenses/Apache-2.0","name":"Apache License 2.0","free":true,"osi":true}},"github":"https://github.com/projectpythia/xbatcher-deep-learning","copyright":"2024","affiliations":[{"id":"UAlbany","name":"University at Albany (SUNY)","department":"Atmospheric and Environmental Sciences","url":"https://www.albany.edu/daes"},{"id":"CISL","name":"NSF National Center for Atmospheric Research","department":"Computational and Information Systems Lab","url":"https://www.cisl.ucar.edu"},{"id":"Unidata","name":"NSF Unidata","url":"https://www.unidata.ucar.edu"},{"id":"Argonne","name":"Argonne National Laboratory","department":"Environmental Science Division","url":"https://www.anl.gov/evs"},{"id":"CarbonPlan","name":"CarbonPlan","url":"https://carbonplan.org"},{"id":"NVIDIA","name":"NVIDIA Corporation","url":"https://www.nvidia.com/"}],"edit_url":"https://github.com/projectpythia/xbatcher-deep-learning/blob/main/README.md","thumbnail":"/xbatcher-deep-learning/build/thumbnail-792dcbf225d8c518cab2c2bbb3c0be86.png","exports":[{"format":"md","filename":"README.md","url":"/xbatcher-deep-learning/build/README-61687755d6d1230172da752b63a2c4c5.md"}]},"mdast":{"type":"root","children":[{"type":"block","children":[{"type":"image","url":"/xbatcher-deep-learning/build/thumbnail-792dcbf225d8c518cab2c2bbb3c0be86.png","alt":"thumbnail","width":300,"key":"En06LZHs3l","urlSource":"thumbnails/thumbnail.png"},{"type":"paragraph","position":{"start":{"line":5,"column":1},"end":{"line":7,"column":1}},"children":[{"type":"link","url":"https://github.com/ProjectPythia/cookbook-template/actions/workflows/nightly-build.yaml","position":{"start":{"line":5,"column":1},"end":{"line":5,"column":1}},"children":[{"type":"image","url":"/xbatcher-deep-learning/build/06605fa84b8680f0497b7822b6283a3e.svg","alt":"nightly-build","position":{"start":{"line":5,"column":1},"end":{"line":5,"column":1}},"key":"H7oUtKL9Nu","urlSource":"https://github.com/ProjectPythia/cookbook-template/actions/workflows/nightly-build.yaml/badge.svg"}],"urlSource":"https://github.com/ProjectPythia/cookbook-template/actions/workflows/nightly-build.yaml","error":true,"key":"xGe1EvFgeF"},{"type":"text","value":"\n","position":{"start":{"line":5,"column":1},"end":{"line":5,"column":1}},"key":"sDMrmmyuFw"},{"type":"link","url":"https://binder.projectpythia.org/v2/gh/ProjectPythia/cookbook-template/main?labpath=notebooks","position":{"start":{"line":5,"column":1},"end":{"line":5,"column":1}},"children":[{"type":"image","url":"/xbatcher-deep-learning/build/31e3f387ea168934ca949c27e9927ea4.svg","alt":"Binder","position":{"start":{"line":5,"column":1},"end":{"line":5,"column":1}},"key":"OMEOKExcx7","urlSource":"https://binder.projectpythia.org/badge_logo.svg"}],"urlSource":"https://binder.projectpythia.org/v2/gh/ProjectPythia/cookbook-template/main?labpath=notebooks","key":"ek44qeOwJx"},{"type":"text","value":"\n","position":{"start":{"line":5,"column":1},"end":{"line":5,"column":1}},"key":"xdEeXSI4ED"},{"type":"link","url":"https://doi.org/10.5281/zenodo.475509405","position":{"start":{"line":5,"column":1},"end":{"line":5,"column":1}},"children":[{"type":"image","url":"/xbatcher-deep-learning/build/72a08caa5cbe5f9cce5999dbd1a81dfd.svg","alt":"DOI","position":{"start":{"line":5,"column":1},"end":{"line":5,"column":1}},"key":"eT7lPxbKCP","urlSource":"https://zenodo.org/badge/475509405.svg"}],"urlSource":"https://zenodo.org/badge/latestdoi/475509405","data":{"doi":"10.5281/zenodo.475509405"},"internal":false,"protocol":"doi","key":"fXC9a38inz"}],"key":"yjuA1KxbYX"},{"type":"paragraph","position":{"start":{"line":9,"column":1},"end":{"line":9,"column":1}},"children":[{"type":"emphasis","position":{"start":{"line":9,"column":1},"end":{"line":9,"column":1}},"children":[{"type":"text","value":"See the ","position":{"start":{"line":9,"column":1},"end":{"line":9,"column":1}},"key":"ElKDhFUtMl"},{"type":"link","url":"https://projectpythia.org/cookbook-guide","position":{"start":{"line":9,"column":1},"end":{"line":9,"column":1}},"children":[{"type":"text","value":"Cookbook Contributor’s Guide","position":{"start":{"line":9,"column":1},"end":{"line":9,"column":1}},"key":"dIEtvoqLPz"}],"urlSource":"https://projectpythia.org/cookbook-guide","key":"kbeWoF4VBS"},{"type":"text","value":" for step-by-step instructions on how to create your new Cookbook and get it hosted on the ","position":{"start":{"line":9,"column":1},"end":{"line":9,"column":1}},"key":"tZHeswWz6N"},{"type":"link","url":"https://cookbooks.projectpythia.org","position":{"start":{"line":9,"column":1},"end":{"line":9,"column":1}},"children":[{"type":"text","value":"Pythia Cookbook Gallery","position":{"start":{"line":9,"column":1},"end":{"line":9,"column":1}},"key":"mwrrENbOGp"}],"urlSource":"https://cookbooks.projectpythia.org","key":"v0Kte9xrLe"},{"type":"text","value":"!","position":{"start":{"line":9,"column":1},"end":{"line":9,"column":1}},"key":"NMdjNW3Lto"}],"key":"q4bv00gTxy"}],"key":"YtL0Zl2pqm"},{"type":"paragraph","position":{"start":{"line":11,"column":1},"end":{"line":11,"column":1}},"children":[{"type":"text","value":"This Project Pythia Cookbook covers ... (replace ","position":{"start":{"line":11,"column":1},"end":{"line":11,"column":1}},"key":"d9jIoiKbbY"},{"type":"inlineCode","value":"...","position":{"start":{"line":11,"column":1},"end":{"line":11,"column":1}},"key":"CPuyz2oqWA"},{"type":"text","value":" with the main subject of your cookbook ... e.g., ","position":{"start":{"line":11,"column":1},"end":{"line":11,"column":1}},"key":"IC8EyJHmJd"},{"type":"emphasis","position":{"start":{"line":11,"column":1},"end":{"line":11,"column":1}},"children":[{"type":"text","value":"working with radar data in Python","position":{"start":{"line":11,"column":1},"end":{"line":11,"column":1}},"key":"aBO2mEQUjr"}],"key":"KlJX8tfpqT"},{"type":"text","value":")","position":{"start":{"line":11,"column":1},"end":{"line":11,"column":1}},"key":"QjTv1kfKbE"}],"key":"BSgV7JFVoZ"},{"type":"heading","depth":2,"position":{"start":{"line":13,"column":1},"end":{"line":13,"column":1}},"children":[{"type":"text","value":"Motivation","position":{"start":{"line":13,"column":1},"end":{"line":13,"column":1}},"key":"WWP24GAyy9"}],"identifier":"motivation","label":"Motivation","html_id":"motivation","implicit":true,"key":"N6anJ4kBMB"},{"type":"paragraph","position":{"start":{"line":15,"column":1},"end":{"line":15,"column":1}},"children":[{"type":"text","value":"(Add a few sentences stating why this cookbook will be useful. What skills will you, “the chef”, gain once you have reached the end of the cookbook?)","position":{"start":{"line":15,"column":1},"end":{"line":15,"column":1}},"key":"VQKRBIfvff"}],"key":"TQmSY9Mzmv"},{"type":"heading","depth":2,"position":{"start":{"line":17,"column":1},"end":{"line":17,"column":1}},"children":[{"type":"text","value":"Authors","position":{"start":{"line":17,"column":1},"end":{"line":17,"column":1}},"key":"O7ZSwJxWgC"}],"identifier":"authors","label":"Authors","html_id":"authors","implicit":true,"key":"NzjDXlRnmi"},{"type":"paragraph","position":{"start":{"line":19,"column":1},"end":{"line":19,"column":1}},"children":[{"type":"link","url":"https://github.com/first-author1","position":{"start":{"line":19,"column":1},"end":{"line":19,"column":1}},"children":[{"type":"text","value":"First Author","position":{"start":{"line":19,"column":1},"end":{"line":19,"column":1}},"key":"F938zdtlqn"}],"urlSource":"https://github.com/first-author1","error":true,"key":"EiiFNTJPbL"},{"type":"text","value":", ","position":{"start":{"line":19,"column":1},"end":{"line":19,"column":1}},"key":"MGCbDjp7t5"},{"type":"link","url":"https://github.com/second-author2","position":{"start":{"line":19,"column":1},"end":{"line":19,"column":1}},"children":[{"type":"text","value":"Second Author","position":{"start":{"line":19,"column":1},"end":{"line":19,"column":1}},"key":"PhHdj9oU84"}],"urlSource":"https://github.com/second-author2","error":true,"key":"ltJhDMV8J3"},{"type":"text","value":", etc. ","position":{"start":{"line":19,"column":1},"end":{"line":19,"column":1}},"key":"fptnMhzlrb"},{"type":"emphasis","position":{"start":{"line":19,"column":1},"end":{"line":19,"column":1}},"children":[{"type":"text","value":"Acknowledge primary content authors here","position":{"start":{"line":19,"column":1},"end":{"line":19,"column":1}},"key":"m9hEOhcND7"}],"key":"MOAXvsKZ7T"}],"key":"R4eUbHMO5d"},{"type":"heading","depth":3,"position":{"start":{"line":21,"column":1},"end":{"line":21,"column":1}},"children":[{"type":"text","value":"Contributors","position":{"start":{"line":21,"column":1},"end":{"line":21,"column":1}},"key":"VGU6avVPKp"}],"identifier":"contributors","label":"Contributors","html_id":"contributors","implicit":true,"key":"eixAThSrRJ"},{"type":"link","url":"https://github.com/ProjectPythia/cookbook-template/graphs/contributors","children":[{"type":"image","url":"/xbatcher-deep-learning/build/9dd7ab81e0df25b8a23d08cf1d00bf8b.svg","key":"WrehgK6hPm","urlSource":"https://contrib.rocks/image?repo=ProjectPythia/cookbook-template"}],"urlSource":"https://github.com/ProjectPythia/cookbook-template/graphs/contributors","error":true,"key":"imsFLBN0uR"},{"type":"heading","depth":2,"position":{"start":{"line":27,"column":1},"end":{"line":27,"column":1}},"children":[{"type":"text","value":"Structure","position":{"start":{"line":27,"column":1},"end":{"line":27,"column":1}},"key":"JbndD6HGAG"}],"identifier":"structure","label":"Structure","html_id":"structure","implicit":true,"key":"h2Q1o9Va8r"},{"type":"paragraph","position":{"start":{"line":29,"column":1},"end":{"line":29,"column":1}},"children":[{"type":"text","value":"(State one or more sections that will comprise the notebook. E.g., ","position":{"start":{"line":29,"column":1},"end":{"line":29,"column":1}},"key":"CL0DsQVl33"},{"type":"emphasis","position":{"start":{"line":29,"column":1},"end":{"line":29,"column":1}},"children":[{"type":"text","value":"This cookbook is broken up into two main sections - “Foundations” and “Example Workflows.”","position":{"start":{"line":29,"column":1},"end":{"line":29,"column":1}},"key":"XsyDftG1a4"}],"key":"xaNV1iNB5N"},{"type":"text","value":" Then, describe each section below.)","position":{"start":{"line":29,"column":1},"end":{"line":29,"column":1}},"key":"k7NrBlkfSs"}],"key":"mzDELoYquv"},{"type":"heading","depth":3,"position":{"start":{"line":31,"column":1},"end":{"line":31,"column":1}},"children":[{"type":"text","value":"Section 1 ( Replace with the title of this section, e.g. “Foundations” )","position":{"start":{"line":31,"column":1},"end":{"line":31,"column":1}},"key":"NuziDTyjRn"}],"identifier":"section-1-replace-with-the-title-of-this-section-e-g-foundations","label":"Section 1 ( Replace with the title of this section, e.g. “Foundations” )","html_id":"section-1-replace-with-the-title-of-this-section-e-g-foundations","implicit":true,"key":"n5UDozPoiJ"},{"type":"paragraph","position":{"start":{"line":33,"column":1},"end":{"line":33,"column":1}},"children":[{"type":"text","value":"(Add content for this section, e.g., \"The foundational content includes ... \")","position":{"start":{"line":33,"column":1},"end":{"line":33,"column":1}},"key":"uhwKq4skRV"}],"key":"A62l1O7otW"},{"type":"heading","depth":3,"position":{"start":{"line":35,"column":1},"end":{"line":35,"column":1}},"children":[{"type":"text","value":"Section 2 ( Replace with the title of this section, e.g. “Example workflows” )","position":{"start":{"line":35,"column":1},"end":{"line":35,"column":1}},"key":"m08FLMESWa"}],"identifier":"section-2-replace-with-the-title-of-this-section-e-g-example-workflows","label":"Section 2 ( Replace with the title of this section, e.g. “Example workflows” )","html_id":"section-2-replace-with-the-title-of-this-section-e-g-example-workflows","implicit":true,"key":"TX89Wpf8vZ"},{"type":"paragraph","position":{"start":{"line":37,"column":1},"end":{"line":37,"column":1}},"children":[{"type":"text","value":"(Add content for this section, e.g., \"Example workflows include ... \")","position":{"start":{"line":37,"column":1},"end":{"line":37,"column":1}},"key":"A5cV0GL60u"}],"key":"tKE2aPzUGn"},{"type":"heading","depth":2,"position":{"start":{"line":39,"column":1},"end":{"line":39,"column":1}},"children":[{"type":"text","value":"Running the Notebooks","position":{"start":{"line":39,"column":1},"end":{"line":39,"column":1}},"key":"sGuGdgMxFp"}],"identifier":"running-the-notebooks","label":"Running the Notebooks","html_id":"running-the-notebooks","implicit":true,"key":"S6LQDXxu41"},{"type":"paragraph","position":{"start":{"line":41,"column":1},"end":{"line":41,"column":1}},"children":[{"type":"text","value":"You can either run the notebook using ","position":{"start":{"line":41,"column":1},"end":{"line":41,"column":1}},"key":"e6hLBZ1Nlv"},{"type":"link","url":"https://binder.projectpythia.org/","position":{"start":{"line":41,"column":1},"end":{"line":41,"column":1}},"children":[{"type":"text","value":"Binder","position":{"start":{"line":41,"column":1},"end":{"line":41,"column":1}},"key":"WPruaA7E89"}],"urlSource":"https://binder.projectpythia.org/","key":"NwrSYj1k3M"},{"type":"text","value":" or on your local machine.","position":{"start":{"line":41,"column":1},"end":{"line":41,"column":1}},"key":"f75bVdamYQ"}],"key":"v0dNy3iopL"},{"type":"heading","depth":3,"position":{"start":{"line":43,"column":1},"end":{"line":43,"column":1}},"children":[{"type":"text","value":"Running on Binder","position":{"start":{"line":43,"column":1},"end":{"line":43,"column":1}},"key":"T9AP9sck5B"}],"identifier":"running-on-binder","label":"Running on Binder","html_id":"running-on-binder","implicit":true,"key":"yhft24yt4P"},{"type":"paragraph","position":{"start":{"line":45,"column":1},"end":{"line":58,"column":1}},"children":[{"type":"text","value":"The simplest way to interact with a Jupyter Notebook is through\n","position":{"start":{"line":45,"column":1},"end":{"line":45,"column":1}},"key":"pe0Oiwmlfv"},{"type":"link","url":"https://binder.projectpythia.org/","position":{"start":{"line":45,"column":1},"end":{"line":45,"column":1}},"children":[{"type":"text","value":"Binder","position":{"start":{"line":45,"column":1},"end":{"line":45,"column":1}},"key":"R5u7CUCsGM"}],"urlSource":"https://binder.projectpythia.org/","key":"Wy6XAScrST"},{"type":"text","value":", which enables the execution of a\n","position":{"start":{"line":45,"column":1},"end":{"line":45,"column":1}},"key":"qjFt6ge2l7"},{"type":"link","url":"https://jupyterbook.org","position":{"start":{"line":45,"column":1},"end":{"line":45,"column":1}},"children":[{"type":"text","value":"Jupyter Book","position":{"start":{"line":45,"column":1},"end":{"line":45,"column":1}},"key":"lquQ6A1d9g"}],"urlSource":"https://jupyterbook.org","key":"ZBt5fXC8Ma"},{"type":"text","value":" in the cloud. The details of how this works are not\nimportant for now. All you need to know is how to launch a Pythia\nCookbooks chapter via Binder. Simply navigate your mouse to\nthe top right corner of the book chapter you are viewing and click\non the rocket ship icon, (see figure below), and be sure to select\n“launch Binder”. After a moment you should be presented with a\nnotebook that you can interact with. I.e. you’ll be able to execute\nand even change the example programs. You’ll see that the code cells\nhave no output at first, until you execute them by pressing\n","position":{"start":{"line":45,"column":1},"end":{"line":45,"column":1}},"key":"mWOW7esQjq"},{"type":"keyboard","children":[{"type":"text","value":"Shift","key":"ugOExTrYik"}],"key":"mQQ49sAZey"},{"type":"text","value":"+","position":{"start":{"line":45,"column":1},"end":{"line":45,"column":1}},"key":"FJmeL99rW6"},{"type":"keyboard","children":[{"type":"text","value":"Enter","key":"MSaw4gf7Nl"}],"key":"tfXOen5GqK"},{"type":"text","value":". Complete details on how to interact with\na live Jupyter notebook are described in ","position":{"start":{"line":45,"column":1},"end":{"line":45,"column":1}},"key":"pisZTsyaaC"},{"type":"link","url":"https://foundations.projectpythia.org/foundations/getting-started-jupyter","position":{"start":{"line":45,"column":1},"end":{"line":45,"column":1}},"children":[{"type":"text","value":"Getting Started with\nJupyter","position":{"start":{"line":45,"column":1},"end":{"line":45,"column":1}},"key":"l68hXfI8fU"}],"urlSource":"https://foundations.projectpythia.org/foundations/getting-started-jupyter","key":"kPPOYs5pO0"},{"type":"text","value":".","position":{"start":{"line":45,"column":1},"end":{"line":45,"column":1}},"key":"krEQfbZHHU"}],"key":"doQAVB6bLA"},{"type":"paragraph","position":{"start":{"line":60,"column":1},"end":{"line":62,"column":1}},"children":[{"type":"text","value":"Note, not all Cookbook chapters are executable. If you do not see\nthe rocket ship icon, such as on this page, you are not viewing an\nexecutable book chapter.","position":{"start":{"line":60,"column":1},"end":{"line":60,"column":1}},"key":"kktq29gKCL"}],"key":"XbID0H5rT8"},{"type":"heading","depth":3,"position":{"start":{"line":65,"column":1},"end":{"line":65,"column":1}},"children":[{"type":"text","value":"Running on Your Own Machine","position":{"start":{"line":65,"column":1},"end":{"line":65,"column":1}},"key":"dSl9OfOTnH"}],"identifier":"running-on-your-own-machine","label":"Running on Your Own Machine","html_id":"running-on-your-own-machine","implicit":true,"key":"CivSg2rmNs"},{"type":"paragraph","position":{"start":{"line":67,"column":1},"end":{"line":67,"column":1}},"children":[{"type":"text","value":"If you are interested in running this material locally on your computer, you will need to follow this workflow:","position":{"start":{"line":67,"column":1},"end":{"line":67,"column":1}},"key":"Y6h6Zs0Jxr"}],"key":"Xxf58biOsy"},{"type":"paragraph","position":{"start":{"line":69,"column":1},"end":{"line":69,"column":1}},"children":[{"type":"text","value":"(Replace “cookbook-example” with the title of your cookbooks)","position":{"start":{"line":69,"column":1},"end":{"line":69,"column":1}},"key":"DydAZ57wDR"}],"key":"hOiX96IVW8"},{"type":"list","ordered":true,"start":1,"spread":false,"position":{"start":{"line":71,"column":1},"end":{"line":90,"column":1}},"children":[{"type":"listItem","spread":true,"position":{"start":{"line":71,"column":1},"end":{"line":76,"column":1}},"children":[{"type":"paragraph","position":{"start":{"line":71,"column":1},"end":{"line":71,"column":1}},"children":[{"type":"text","value":"Clone the ","position":{"start":{"line":71,"column":1},"end":{"line":71,"column":1}},"key":"D6zmNFOauZ"},{"type":"inlineCode","value":"https://github.com/ProjectPythia/cookbook-example","position":{"start":{"line":71,"column":1},"end":{"line":71,"column":1}},"key":"rxvfgtHbob"},{"type":"text","value":" repository:","position":{"start":{"line":71,"column":1},"end":{"line":71,"column":1}},"key":"tGDT0UtgMS"}],"key":"Z2LNBgwhGy"},{"type":"code","lang":"bash","value":" git clone https://github.com/ProjectPythia/cookbook-example.git","position":{"start":{"line":73,"column":1},"end":{"line":75,"column":1}},"key":"MiVsGY0EN0"}],"key":"gpRpXpLH4V"},{"type":"listItem","spread":true,"position":{"start":{"line":77,"column":1},"end":{"line":80,"column":1}},"children":[{"type":"paragraph","position":{"start":{"line":77,"column":1},"end":{"line":77,"column":1}},"children":[{"type":"text","value":"Move into the ","position":{"start":{"line":77,"column":1},"end":{"line":77,"column":1}},"key":"ftIxJt9F3p"},{"type":"inlineCode","value":"cookbook-example","position":{"start":{"line":77,"column":1},"end":{"line":77,"column":1}},"key":"VmCOjW4HPy"},{"type":"text","value":" directory","position":{"start":{"line":77,"column":1},"end":{"line":77,"column":1}},"key":"tjAnwwiN2x"}],"key":"S79zq8GHWH"},{"type":"code","lang":"bash","value":"cd cookbook-example","position":{"start":{"line":78,"column":1},"end":{"line":80,"column":1}},"key":"A8ew3TcAxC"}],"key":"Hp0Bprm0ih"},{"type":"listItem","spread":true,"position":{"start":{"line":81,"column":1},"end":{"line":85,"column":1}},"children":[{"type":"paragraph","position":{"start":{"line":81,"column":1},"end":{"line":81,"column":1}},"children":[{"type":"text","value":"Create and activate your conda environment from the ","position":{"start":{"line":81,"column":1},"end":{"line":81,"column":1}},"key":"EXrDU0BPWU"},{"type":"inlineCode","value":"environment.yml","position":{"start":{"line":81,"column":1},"end":{"line":81,"column":1}},"key":"vLXDxGoNgT"},{"type":"text","value":" file","position":{"start":{"line":81,"column":1},"end":{"line":81,"column":1}},"key":"hh7RS4QhGN"}],"key":"xWHnBju4oK"},{"type":"code","lang":"bash","value":"conda env create -f environment.yml\nconda activate cookbook-example","position":{"start":{"line":82,"column":1},"end":{"line":85,"column":1}},"key":"kTpC1F6K1g"}],"key":"b5z2YHsIns"},{"type":"listItem","spread":true,"position":{"start":{"line":86,"column":1},"end":{"line":90,"column":1}},"children":[{"type":"paragraph","position":{"start":{"line":86,"column":1},"end":{"line":86,"column":1}},"children":[{"type":"text","value":"Move into the ","position":{"start":{"line":86,"column":1},"end":{"line":86,"column":1}},"key":"MRrP6r1Zsg"},{"type":"inlineCode","value":"notebooks","position":{"start":{"line":86,"column":1},"end":{"line":86,"column":1}},"key":"IOZPfxjmDn"},{"type":"text","value":" directory and start up Jupyterlab","position":{"start":{"line":86,"column":1},"end":{"line":86,"column":1}},"key":"PD3pgMe7nT"}],"key":"VNkNaWrxnL"},{"type":"code","lang":"bash","value":"cd notebooks/\njupyter lab","position":{"start":{"line":87,"column":1},"end":{"line":90,"column":1}},"key":"A2sV9G4QtK"}],"key":"I5DDF19A4X"}],"key":"NDhJgaxRWa"}],"key":"YhbA4kszuH"}],"key":"NFXYt8aq3u"},"references":{"cite":{"order":[],"data":{}}},"footer":{"navigation":{"next":{"title":"How to Cite This Cookbook","url":"/notebooks/how-to-cite","group":"Preamble"}}},"domain":"http://localhost:3000"}